conda_ops/__init__.py
conda_ops/_paths.py
conda_ops/commands.py
conda_ops/commands_env.py
conda_ops/commands_lockfile.py
conda_ops/commands_proj.py
conda_ops/commands_reqs.py
conda_ops/conda_config.py
conda_ops/conda_ops_later.py
conda_ops/conda_ops_parser.py
conda_ops/conftest.py
conda_ops/decorators.py
conda_ops/env_handler.py
conda_ops/kvstore.py
conda_ops/python_api.py
conda_ops/requirements.py
conda_ops/split_requirements.py
conda_ops/utils.py
conda_ops-0.4.dist-info/LICENSE
conda_ops-0.4.dist-info/METADATA
conda_ops-0.4.dist-info/WHEEL
conda_ops-0.4.dist-info/entry_points.txt
conda_ops-0.4.dist-info/top_level.txt
conda_ops-0.4.dist-info/RECORD
