Metadata-Version: 2.1
Name: conda-ops
Version: 0.4
Summary: Conda plugin to maintain environments and projects reproducibly.
Author-email: Amy Wooding <amy@wooding.org>
License: MIT License
Project-URL: Homepage, https://github.com/acwooding/conda-ops
Project-URL: Bug Tracker, https://github.com/acwooding/conda-ops/issues
Requires-Python: >=3.7
License-File: LICENSE
Requires-Dist: conda
Provides-Extra: linting
Requires-Dist: black ; extra == 'linting'
Requires-Dist: flake8 ; extra == 'linting'
Requires-Dist: pylint ; extra == 'linting'
Provides-Extra: test
Requires-Dist: pytest >=6.0 ; extra == 'test'
Requires-Dist: coverage ; extra == 'test'
Requires-Dist: pytest-mock ; extra == 'test'
